LICENSE
MANIFEST.in
requirements.txt
setup.py
docker_registry_index/__init__.py
docker_registry_index/dynamodb.py
docker_registry_index/dynamodb_config.py
docker_registry_index/dynamodb_util.py
docker_registry_index_dynamodb.egg-info/PKG-INFO
docker_registry_index_dynamodb.egg-info/SOURCES.txt
docker_registry_index_dynamodb.egg-info/dependency_links.txt
docker_registry_index_dynamodb.egg-info/requires.txt
docker_registry_index_dynamodb.egg-info/top_level.txt