Metadata-Version: 1.1
Name: docker-registry-index-dynamodb
Version: 0.1.0
Summary: Docker registry Amazon AWS DynamoDB index database
Home-page: https://github.com/donlaidlaw/docker-registry-index-dynamodb
Author: Don Laidlaw
Author-email: don@donlaidlaw.ca
License: 
